FindingCount.py
HostInfo.py
IdentifiedServices.py
LDAPinfo.py
MergeNessus.py
NessusPluginHosts.py
PrinterInfo.py
RemoveHost.py
SynScanSummary.py
nessus_plugin_hosts-2.0.8.dist-info/METADATA
nessus_plugin_hosts-2.0.8.dist-info/WHEEL
nessus_plugin_hosts-2.0.8.dist-info/entry_points.txt
nessus_plugin_hosts-2.0.8.dist-info/top_level.txt
nessus_plugin_hosts-2.0.8.dist-info/RECORD
