Metadata-Version: 2.4
Name: nessus-plugin-hosts
Version: 2.0.8
Summary: A collection of Python CLI tools for parsing and summarizing Nessus .nessus scan results.
Author-email: Defensive Origins <info@defensiveorigins.com>
Maintainer-email: Defensive Origins <info@defensiveorigins.com>
License: Proprietary
Project-URL: Homepage, https://github.com/DefensiveOrigins/NessusPluginHosts
Project-URL: Repository, https://github.com/DefensiveOrigins/NessusPluginHosts
Project-URL: Issues, https://github.com/DefensiveOrigins/NessusPluginHosts/issues
Keywords: nessus,vulnerability-scanning,security,reporting,xml,cli
Classifier: Development Status :: 4 - Beta
Classifier: Intended Audience :: Information Technology
Classifier: Intended Audience :: System Administrators
Classifier: License :: OSI Approved :: MIT License
Classifier: Programming Language :: Python
Classifier: Programming Language :: Python :: 3
Classifier: Programming Language :: Python :: 3 :: Only
Classifier: Programming Language :: Python :: 3.8
Classifier: Programming Language :: Python :: 3.9
Classifier: Programming Language :: Python :: 3.10
Classifier: Programming Language :: Python :: 3.11
Classifier: Environment :: Console
Classifier: Topic :: Security
Classifier: Topic :: System :: Networking
Classifier: Topic :: Utilities
Requires-Python: >=3.8
